{
	"description": "项目配置文件。",
	"setting": {
		"urlCheck": false,
		"es6": false,
		"postcss": true,
		"minified": true,
		"newFeature": true
	},
	"miniprogramRoot": "dist/",
	"compileType": "miniprogram",
	"qcloudRoot": "server/",
	"appid": "wx1cf3c33d21786f00",
	"projectname": "aijiu",
	"libVersion": "2.1.1",
	"condition": {
		"search": {
			"current": -1,
			"list": []
		},
		"conversation": {
			"current": -1,
			"list": []
		},
		"game": {
			"currentL": -1,
			"list": []
		},
		"miniprogram": {
			"current": -1,
			"list": []
		}
	}
}